{"_meta":{"store":"feandrea","pageSlug":"05_kratzbaeume","pageId":"0969F474-6991-44A8-864E-BAC3587E4935","pageName":"Kratzbäume","extractedAt":"2026-05-23","scrollHeight":9929,"domRowsTotal":12,"note":"Kratzbaum-Kategorie-Page mit Hero plus mehreren Image-Modulen plus 2 eingebetteten Videos plus ProductCollection 40 ASINs plus Tile-Pair am Ende. Multi-Image plus Video Sequenz vor Vollkatalog."},"modules":[{"domRowIdx":0,"widgetType":"Header","top":99,"height":400,"imgCount":3,"ctaLabels":["Feandrea by SONGMICS HOME","Kratzbäume","Folgen","Startseite","Sonderangebote"],"note":"Nav header"},{"domRowIdx":1,"widgetType":"EditorialRow","top":507,"height":743,"imgCount":1,"productCount":0,"ctaLabels":["Produkte ansehen"],"note":"Hero Image full-width banner"},{"domRowIdx":2,"widgetType":"EditorialRow","top":1249,"height":743,"imgCount":0,"videoCount":1,"productCount":0,"note":"Video-Modul Vollformat"},{"domRowIdx":3,"widgetType":"EditorialRow","top":1992,"height":224,"imgCount":0,"productCount":0,"note":"Section Spacer"},{"domRowIdx":4,"widgetType":"EditorialRow","top":2216,"height":371,"imgCount":4,"productCount":0,"note":"Tile-Row 4-fach Sub-Verteiler"},{"domRowIdx":5,"widgetType":"EditorialRow","top":2587,"height":224,"imgCount":0,"productCount":0,"note":"Section Spacer"},{"domRowIdx":6,"widgetType":"EditorialRow","top":2812,"height":743,"imgCount":1,"productCount":0,"ctaLabels":["Produkte ansehen"],"note":"Image-Modul full-width"},{"domRowIdx":7,"widgetType":"EditorialRow","top":3554,"height":743,"imgCount":1,"videoCount":1,"productCount":0,"ctaLabels":["Video abspielen"],"note":"Video-Modul mit Cover-Image plus Play-CTA"},{"domRowIdx":8,"widgetType":"EditorialRow","top":4297,"height":743,"imgCount":1,"productCount":0,"ctaLabels":["Produkte ansehen"],"note":"Image-Modul full-width"},{"domRowIdx":9,"widgetType":"ProductCollection","top":5039,"height":3056,"imgCount":29,"productCount":40,"headings":["Kratzbäume"],"sampleAsins":["B08MPV5Y7G","B0C5QPPNL9","B08XTMNMMZ","B07QL5B313","B0CTQ63ZDP"],"trustSeals":["The Forest Stewardship Council"],"sustainabilityTags":["Nachhaltigeres Beforsten"],"note":"ProductCollection 40 ASINs Kratzbäume Vollkatalog mit FSC-Tag plus Nachhaltigkeits-Marker"},{"domRowIdx":10,"widgetType":"EditorialRow","top":8095,"height":371,"imgCount":2,"productCount":0,"note":"Tile-Pair als Closing"},{"domRowIdx":11,"widgetType":"EditorialRow","top":8466,"height":201,"ctaLabels":["Teilen"],"note":"amazon_share_footer"}]}
